README.md
setup.py
tapi_yandex_direct/__init__.py
tapi_yandex_direct/exceptions.py
tapi_yandex_direct/resource_mapping.py
tapi_yandex_direct/tapi_yandex_direct.py
tapi_yandex_direct/tapi_yandex_direct.pyi
tapi_yandex_direct.egg-info/PKG-INFO
tapi_yandex_direct.egg-info/SOURCES.txt
tapi_yandex_direct.egg-info/dependency_links.txt
tapi_yandex_direct.egg-info/not-zip-safe
tapi_yandex_direct.egg-info/requires.txt
tapi_yandex_direct.egg-info/top_level.txt