Metadata-Version: 2.1
Name: tapi-yandex-direct
Version: 2021.5.29
Summary: Python client for API Yandex Direct
Home-page: https://github.com/pavelmaksimov/tapi-yandex-direct
Author: Pavel Maksimov
Author-email: vur21@ya.ru
License: MIT
Keywords: tapi,wrapper,yandex,metrika,api,direct,яндекс,директ,апи
Platform: UNKNOWN
